russian_protowhat/Feedback.py
russian_protowhat/Reporter.py
russian_protowhat/State.py
russian_protowhat/Test.py
russian_protowhat/__init__.py
russian_protowhat/sct_syntax.py
russian_protowhat/selectors.py
russian_protowhat/setup.py
russian_protowhat/utils.py
russian_protowhat/utils_ast.py
russian_protowhat/utils_messaging.py
russian_protowhat/checks/__init__.py
russian_protowhat/checks/check_bash_history.py
russian_protowhat/checks/check_files.py
russian_protowhat/checks/check_funcs.py
russian_protowhat/checks/check_logic.py
russian_protowhat/checks/check_simple.py
russian_protowhat-1.13.1.dist-info/METADATA
russian_protowhat-1.13.1.dist-info/WHEEL
russian_protowhat-1.13.1.dist-info/top_level.txt
russian_protowhat-1.13.1.dist-info/RECORD
