Metadata-Version: 2.1
Name: russian-protowhat
Version: 1.13.1
Summary: Prototype package for submission correctness testing
Home-page: https://github.com/datacamp/protowhat
Author: Filip Schouwenaars
Author-email: filip@datacamp.com
Maintainer: Jeroen Hermans
Maintainer-email: content-engineering@datacamp.com
Classifier: Programming Language :: Python :: 3
Classifier: License :: OSI Approved :: GNU Affero General Public License v3
Classifier: Operating System :: OS Independent
Requires-Dist: markdown2 (~=2.3.10)
Requires-Dist: jinja2 (==3.0.3)
